{
  "articles": {
    "the": "la/a/nan/an,yo"
  },

  "definite_articles": {
    "some": "kèk",
    "that": "sa",
    "these": "sa yo",
    "this": "sa",
    "those": "sa yo"
  },

  "indefinite_articles": {
    "a": "yon",
    "an": "yon"
  },

  "nouns": {
    "animal": "bèt",
    "arm": "bra",
    "baby": "bebe",
    "bathroom": "chanm pou benyen",
    "beans": "pwa",
    "beef": "bèf",
    "belly": "vant",
    "bird": "zwazo",
    "blood": "san",
    "body": "kò",
    "book": "liv",
    "boy": "ti gason",
    "brother": "frè",
    "butterfly": "papiyon",
    "car": "machin",
    "carrot": "kawòt",
    "cat": "chat",
    "cent": "santim",
    "grapefruit": "chadèk",
    "chair": "chèz",
    "chicken": "poul",
    "church": "legliz",
    "classroom": "sal de klas",
    "coffee": "kafe",
    "color": "koulè",
    "corn": "mayi",
    "cow": "bèf",
    "daughter": "pitit fi",
    "day": "jou",
    "door": "pòt",
    "dog": "chen",
    "dollar": "dola",
    "ear": "zòrèy",
    "eye": "je",
    "father": "papa",
    "finger": "dwèt",
    "fish": "pwason",
    "flower": "flè",
    "food": "manje",
    "four": "kat",
    "fork": "fouchèt",
    "friend": "zanmi",
    "gourde": "goud",
    "girl": "ti fi",
    "goat": "kabrit",
    "grass": "zèb",
    "hand": "men",
    "head": "tèt",
    "home": "lakay",
    "homework": "devwa",
    "hospital": "lopital",
    "horse": "chwal",
    "house": "kay",
    "husband": "mari",
    "job": "travay",
    "juice": "ji",
    "leaf": "fèy",
    "lemon": "sitwon",
    "lie": "manti",
    "lime": "sitwon",
    "market": "mache",
    "meat": "viann",
    "meeting": "randevou",
    "watermelon": "melon",
    "mango": "mango",
    "man": "nonm",
    "money": "lajan",
    "moon": "lalin",
    "morning": "maten",
    "mosquito": "marengwen",
    "mother": "manman",
    "mountain": "mòn",
    "mouth": "bouch",
    "name": "non",
    "nature": "lanati",
    "neck": "kou",
    "night": "nwit",
    "nine": "nèf",
    "no":"non",
    "number": "nimewo",
    "oat": "avwann",
    "one": "youn",
    "orange": "zoranj",
    "payment": "peman",
    "peach": "pèch",
    "pig": "kochon",
    "place": "plas",
    "plantain": "bannann",
    "papaya": "papay",
    "passion fruit": "grenadya",
    "pork": "kochon",
    "rice": "diri",
    "river": "rivyè",
    "road": "wout",
    "rooster": "kòk",
    "room": "chanm",
    "school": "lekòl",
    "sea": "lanmè",
    "seven": "sèt",
    "sheep": "mouton",
    "shop": "boutik",
    "sister": "sè",
    "six": "sis",
    "sky": "syèl",
    "son": "pitit gason",
    "soursop": "kowosòl",
    "stew": "bouyon",
    "spaghetti": "espageti",
    "spoon": "kiyè",
    "star": "zetwal",
    "strawberry": "frèz",
    "street": "lari",
    "sun": "solèy",
    "table": "tab",
    "taxi": "taksi",
    "temperature": "tanperati",
    "ten": "dis",
    "thousand": "mil",
    "three": "twa",
    "time": "lè",
    "tongue": "lang",
    "tree": "pyebwa",
    "turkey": "kodenn",
    "two": "de",
    "water": "dlo",
    "wife": "madanm",
    "woman": "fanm",
    "years": "lane",
    "doctor": "doktè",
    "diarrhea": "dyare",
    "bandage": "pansman",
    "cut": "blese",
    "aids": "sida",
    "english": "anglè",
    "sunday": "dimanch",
    "monday": "lendi",
    "tuesday": "madi",
    "wednesday": "mèkredi",
    "thursday": "jedi",
    "friday": "vandredi",
    "saturday": "samdi"
   
  },

  "numbers": {
    "eight": "uit",
    "eighteen": "dizuit",
    "eighty": "katreven",
    "eighty-eight": "katrevenuit",
    "eighty-five": "katrevensenk",
    "eighty-four": "katrevenkat",
    "eighty-nine": "katrevennèf",
    "eighty-one": "katrevenyen",
    "eighty-seven": "katrevensèt",
    "eighty-six": "katrevensis",
    "eighty-three": "katreventwa",
    "eighty-two": "katrevende",
    "eleven": "onz",
    "fifteen": "kenz",
    "fifty": "senkant",
    "fifty-eight": "senkantuit",
    "fifty-five": "senkantsenk",
    "fifty-four": "senkantkat",
    "fifty-nine": "senkantnèf",
    "fifty-one": "senkantenyen",
    "fifty-seven": "senkantsèt",
    "fifty-six": "senkantsis",
    "fifty-three": "senkanttwa",
    "fifty-two": "senkantde",
    "five": "senk",
    "forty": "karant",
    "forty-eight": "karantuit",
    "forty-five": "karantsenk",
    "forty-four": "karantkat",
    "forty-nine": "karantnèf",
    "forty-one": "karantenyen",
    "forty-seven": "karantsèt",
    "forty-six": "karantsis",
    "forty-three": "karanttwa",
    "forty-two": "karantde",
    "four": "kat",
    "fourteen": "katòz",
    "hundred": "san",
    "nine": "nèf",
    "nineteen": "diznèf",
    "ninety": "katrevendis",
    "ninety-eight": "katrevdizuit",
    "ninety-five": "katrevkenz",
    "ninety-four": "katrevkatòz",
    "ninety-nine": "katrevdiznèf",
    "ninety-one": "katrevonz",
    "ninety-seven": "katrevdisèt",
    "ninety-six": "katrevsèz",
    "ninety-three": "katrevrèz",
    "ninety-two": "katrevdouz",
    "one": "en",
    "seven": "sèt",
    "seventeen": "disèt",
    "seventy": "swasantdis",
    "seventy-eight": "swasantdizuit",
    "seventy-five": "swasantkenz",
    "seventy-four": "swasantkatòz",
    "seventy-nine": "swasantdiznèf",
    "seventy-one": "swasantonz",
    "seventy-seven": "swasantdisèt",
    "seventy-six": "swasantsèz",
    "seventy-three": "swasantrèz",
    "seventy-two": "swasantdouz",
    "six": "sis",
    "sixteen": "sèz",
    "sixty": "swasant",
    "sixty-eight": "swasantuit",
    "sixty-five": "swasantsenk",
    "sixty-four": "swasantkat",
    "sixty-nine": "swasantnèf",
    "sixty-one": "swasantenyen",
    "sixty-seven": "swasantsèt",
    "sixty-six": "swasantsis",
    "sixty-three": "swasanttwa",
    "sixty-two": "swasantde",
    "ten": "dis",
    "thirteen": "trèz",
    "thirty": "trant",
    "thirty-eight": "trantuit",
    "thirty-five": "trantsenk",
    "thirty-four": "trantkat",
    "thirty-nine": "trantnèf",
    "thirty-one": "trantenyen",
    "thirty-seven": "trantsèt",
    "thirty-six": "trantsis",
    "thirty-three": "tranttwa",
    "thirty-two": "trantde",
    "three": "twa",
    "twelve": "douz",
    "twenty": "ven",
    "twenty-eight": "ventyuit",
    "twenty-five": "vensenk",
    "twenty-four": "venkat",
    "twenty-nine": "vennèf",
    "twenty-one": "venyen",
    "twenty-seven": "vensèt",
    "twenty-six": "vensis",
    "twenty-three": "ventwa",
    "twenty-two": "vendè",
    "two": "de",
    "zero": "zewo"
  },

  "interrogatives": {
    "how": "kijan",
    "what": "ki",
    "whatever": "kèlkeswa sa",
    "when": "kilè",
    "whenever": "nenpòt lè",
    "where": "ki kote",
    "why": "poukisa"
  },

  "pronouns": {
    "he": "li",
    "him": "li",
    "i": "mwen",
    "it": "li",
    "me": "mwen",
    "she": "li",
    "them": "yo",
    "they": "yo",
    "us": "nou",
    "we": "nou",
    "you": "ou"
  },

 
  "verbs": {
    "ask": "mande",
    "call": "rele",
    "choose": "chwazi",
    "close": "fèmen",
    "come": "vini",
    "do": "fè",
    "does":"fè",
    "drive": "kondwi",
    "drink": "bwè",
    "eat": "manje",
    "find": "jwenn",
    "give": "bay",
    "go": "ale",
    "have": "genyen",
    "help": "ede",
    "hope": "espere",
    "know": "konnen",
    "let": "kite",
    "lie": "bay manti",
    "like": "renmen",
    "live": "viv",
    "look": "gade",
    "love": "renmen",
    "make": "fè",
    "need": "bezwen",
    "open": "louvri",
    "play": "jwe",
    "read": "li",
    "run": "kouri",
    "say": "di",
    "see": "wè",
    "sit": "chita",
    "sleep": "dòmi",
    "stand": "kanpe",
    "stop": "sispann",
    "take": "pran",
    "talk": "pale",
    "tell": "di",
    "understand": "konprann",
    "wait": "tann",
    "walk": "mache",
    "want": "vle",
    "work": "travay",
    "write": "ekri",
    "goes": "ale",
    "testify": "temwanye",
    "decide": "deside",
    "feel": "santi",
    "show": "montre",
    "speak": "pale",
    "wanna": "vle",
    "meet": "rankontre"
   
    
   
   
  },

  "modal_verbs": { 
    "would": "tap",
    "could": "te ka",
    "can": "ka",
    "did": "te",
    "must": "dwe",
    "should": "ta dwe"
    
   
  },

   "negations": {
    "don't": "pa",
    "doesn't": "pa",
    "didn't": "pat",
    "can't": "pa ka",
    "couldn't": "pat ka",
    "shouldn't": "pata dwe",
    "wouldn't": "patap",
    "mustn't": "pa dwe",
    "ain't" : "pa",
    "isn't": "pa",
    "aren't": "pa",
    "weren't": "pat",
    "wasn't": "pat"
   
  
    
  },

  "pos_pronouns": {
    "her": "li",
    "his": "li",
    "my": "mwen",
    "our": "nou",
    "their": "yo",
    "your": "ou"
  },

  "to_be": {
    "am": "se/ap/genyen",
    "are": "se/ap/genyen",
    "is": "se/ap/genyen",
    "was": "te/tap",
    "were": "te/tap"
  },

  "adjectives": {
    "angry": "fache",
    "bad": "move",
    "beautiful": "bèl",
    "big": "gwo",
    "black": "nwa",
    "blue": "ble",
    "brown": "mawon",
    "busy": "okipe",
    "cold": "fredi",
    "fast": "rapid",
    "fried": "fri",
    "good": "bon",
    "gold": "lò",
    "gray": "gri",
    "green": "vèt",
    "happy": "kontan",
    "here": "la",
    "hot": "cho",
    "hungry": "grangou",
    "long": "long",
    "new": "nouvo",
    "old": "vye",
    "pink": "wòz",
    "purple": "mov",
    "ready": "pare",
    "red": "wouj",
    "sad": "tris",
    "short": "kout",
    "sick": "malad",
    "slow": "ralanti",
    "small": "ti",
    "tired": "fatige",
    "white": "blan",
    "yellow": "jòn",
    "exhausted": "fatige",
    "pregnant": "ansent",
    "creole": "kreyòl"
  },

  "adverbs": {
    "always": "toujou",
    "badly": "mal",
    "early": "bonè",
    "here": "isit la",
    "inside": "anndan",
    "late": "ta",
    "later": "pita",
    "never": "pa janm",
    "now": "kounya",
    "outside": "deyò",
    "quickly": "vit",
    "slowly": "douman",
    "there": "la",
    "together": "ansanm",
    "today": "jodi a",
    "tomorrow": "demèn",
    "well": "byen",
    "yesterday": "yè",
    "maybe": "petèt",
    "already":"deja"
   
  },

  "prepositions": {
    "about": "sou",
    "at": "nan",
    "behind": "dèyè",
    "between": "ant",
    "for": "pou",
    "from": "soti nan",
    "in": "nan",
    "of": "de",
    "on": "sou",
    "over": "anwo",
    "to": "bay",
    "under": "anba",
    "with": "avèk",
    "without": "san"
  },

  "conjunctions": {
    "although": "malgre",
    "and": "e",
    "because": "paske",
    "but": "men",
    "if": "si",
    "or": "oswa",
    "so": "donk",
    "that": "ke",
    "when": "lè",
    "while": "pandan"
  },

  "expressions": {
    "are you ready": "eske ou prè",
    "be careful": "fè atansyon",
    "buckle up": "mete senti ou",
    "because of you": "akoz de ou",
    "cheap": "bon mache",
    "come here": "vin isit",
    "do it": "fè'l",
    "excuse me": "eskize mwen",
    "fried pork": "kochon fri",
    "fried fish": "pwason fri",
    "fried chicken": "poul fri",
    "fried goat": "taso kabrit",
    "fried beef": "taso bèf",
    "give me a kiss": "banm yon bo",
    "god bless you": "bondye beni ou",
    "go home": "al lakay",
    "go sit down": "ale chita",
    "good afternoon": "bòn aprèmidi",
    "good evening": "bonswa",
    "good job": "bon travay",
    "good morning": "bonjou",
    "good night": "bòn nwit",
    "have a good day": "pase yon bon jounen",
    "have a good night": "pase yon bon nwit",
    "how are you": "kòman ou ye",
    "how much does this cost": "konbyen sa koute",
    "how much is it": "konbyen sa koute",
    "how old are you": "ki laj ou",
    "i am fine": "mwen anfòm",
    "i am happy": "mwen kontan",
    "i am hungry": "mwen grangou",
    "i am busy": "mwen okipe",
    "i am sad": "mwen tris",
    "i am thirsty": "mwen swaf",
    "i am tired": "mwen fatige",
    "i am sorry": "mwen dezole",
    "i don't know": "mwen pa konnen",
    "i don't understand": "mwen pa konprann",
    "i understand": "mwen konprann",
    "i love you": "mwen renmen ou",
    "i miss you": "mwen sonje ou",
    "in the evening": "lè swa",
    "in the morning": "le maten",
    "i will clean the kitchen": "map netwaye kizin nan",
    "keep the seatbelt on": "kite senti a tache",
    "keep your hands to yourself": "kite men w nan plas li",
    "last night": "yèswa",
    "let's eat": "an nou manje",
    "let's go": "ann ale",
    "let's work": "an nou travay",
    "listen": "tande",
    "miss you": "mwen sonje ou",
    "no problem": "pa gen pwoblèm",
    "no running": "pa kouri",
    "no cursing": "pa joure",
    "please": "tanpri",
    "see you later": "na wè pita",
    "see you soon": "na wè talè",
    "see you tomorrow": "na wè demen",
    "see you soon my love": "na wè byento amou",
    "sit down": "chita",
    "sit back": "chita dwat",
    "slow down": "ralanti",
    "stop": "sispann",
    "stop screaming": "sispann rele",
    "take care": "pran swen tèt ou",
    "thank you": "mèsi",
    "thank you very much": "mèsi anpil",
    "this morning": "maten an",
    "too expensive": "twò chè",
    "wait": "tann",
    "wait for me": "ret tann mwen",
    "what happened": "kisa ki genyen",
    "what time is it": "ki lè li ye",
    "where are you": "kote ou ye la",
    "where are you going": "ki kote ou prale la",
    "why are you crying": "pou kisa wap krye",
    "you are welcome": "pa gen pwoblèm",
    "you need to listen": "ou dwe tande",
    "what's up": "sak pase",
    "i'm sorry": "mwen regret sa",
    "help": "anmwe",
    "a little bit": "piti piti",
    "a lot": "anpil",
    "is everything ok": "tout bagay anfòm",
    "not now": "pa kounya",
    "everywhere": "toupatou",
    "nothing": "anyen",
    "almost": "preske",
    "watch out": "atansyon",
    "hurry": "prese prese",
    "i'm in a hurry": "mwen prese",
    "divide this among you": "separe sa antre nou",
    "this afternoon": "aprèmidi a",
    "i'm not too well": "mwen pa trò byen",
    "there was an accident": "te gen yon aksidan",
    "where does it hurt you": "ki kote kap fè ou mal",
    "i have diarrhea": "mwen gen dyare",
    "i feel like vomiting": "mwen anvi vomi",
    "i'm dizzy": "tèt mwen ap vire",
    "why": "poukisa",
    "i'm not feeling well": "mwen pa santim byen",
    "what": "kisa",
    "when": "kilè",
    "who": "ki moun",
    "how": "kijan",
    "which": "kiyès",
    "who is there": "ki moun ki la",
    "what do you want": "kisa ou vle",
    "what would you like": "kisa wap pran",
    "what is that": "kisa sa ye",
    "what's the matter": "sak genyen",
    "who speaks english": "kiyes ki pale anglè",
    "what do they call": "kijan yo rele",
    "she is pregnant": "li ansent",
    "i love my mother": "mwen renmen manman mwen",
    "where do you live": "ki kote ou rete",
    "what happened to you": "kisa ki rive ou",
    "Do you have any children": "eske ou gen pitit",
    "i'm going to the beach": "mwen pral nan lanmè",
    "i'm going to school": "mwen pral lekòl",
    "i'm going to church": "mwen pral legliz",
    "i'm going to the party": "mwen pral nan fèt"
  
   
   
    
  }
}
